pytest_ansible/__init__.py
pytest_ansible/_version.py
pytest_ansible/errors.py
pytest_ansible/fixtures.py
pytest_ansible/has_version.py
pytest_ansible/molecule.py
pytest_ansible/plugin.py
pytest_ansible/py.typed
pytest_ansible/results.py
pytest_ansible/units.py
pytest_ansible/host_manager/__init__.py
pytest_ansible/host_manager/base.py
pytest_ansible/host_manager/utils.py
pytest_ansible/host_manager/v213.py
pytest_ansible/module_dispatcher/__init__.py
pytest_ansible/module_dispatcher/v213.py
pytest_ansible-25.11.1.dist-info/licenses/LICENSE
pytest_ansible-25.11.1.dist-info/METADATA
pytest_ansible-25.11.1.dist-info/WHEEL
pytest_ansible-25.11.1.dist-info/entry_points.txt
pytest_ansible-25.11.1.dist-info/top_level.txt
pytest_ansible-25.11.1.dist-info/RECORD
