Metadata-Version: 2.4
Name: pytest-ansible
Version: 25.11.1
Summary: Plugin for pytest to simplify calling ansible modules from tests or fixtures
Author-email: Ansible by Red Hat <info@ansible.com>
Maintainer-email: Ansible by Red Hat <info@ansible.com>
License: MIT
Project-URL: changelog, https://github.com/ansible/pytest-ansible/releases
Project-URL: documentation, https://github.com/ansible/pytest-ansible
Project-URL: homepage, https://github.com/ansible/pytest-ansible
Project-URL: repository, https://github.com/ansible/pytest-ansible
Keywords: ansible,testing,pytest
Classifier: Development Status :: 5 - Production/Stable
Classifier: Intended Audience :: Developers
Classifier: License :: OSI Approved :: MIT License
Classifier: Operating System :: OS Independent
Classifier: Topic :: Software Development :: Testing
Classifier: Topic :: Software Development :: Quality Assurance
Classifier: Topic :: Utilities
Classifier: Programming Language :: Python
Classifier: Programming Language :: Python :: 3
Classifier: Programming Language :: Python :: 3.10
Classifier: Programming Language :: Python :: 3.11
Classifier: Programming Language :: Python :: 3.12
Classifier: Programming Language :: Python :: 3.13
Requires-Python: >=3.10
License-File: LICENSE
Requires-Dist: ansible-core>=2.17.14
Requires-Dist: ansible-compat>=25.8.2
Requires-Dist: cffi>=1.17.1
Requires-Dist: packaging>=25.0
Requires-Dist: pytest>=6
Requires-Dist: pytest-plus>=0.8.1
Requires-Dist: pytest-sugar>=1.1.1
Requires-Dist: pytest-xdist>=3.8.0
Requires-Dist: typing-extensions>=4.15.0
Dynamic: license-file
